unicon/__init__.py
unicon/logs.cpython-312-darwin.so
unicon/patterns.cpython-312-darwin.so
unicon/settings.cpython-312-darwin.so
unicon/sshutils.cpython-312-darwin.so
unicon/type_checkers.cpython-312-darwin.so
unicon/utils.cpython-312-darwin.so
unicon/adapters/__init__.py
unicon/adapters/topology.cpython-312-darwin.so
unicon/bases/__init__.py
unicon/bases/connection.cpython-312-darwin.so
unicon/bases/settings.cpython-312-darwin.so
unicon/bases/synchronize.cpython-312-darwin.so
unicon/bases/linux/__init__.py
unicon/bases/linux/connection.cpython-312-darwin.so
unicon/bases/linux/connection_provider.cpython-312-darwin.so
unicon/bases/linux/services.cpython-312-darwin.so
unicon/bases/routers/__init__.py
unicon/bases/routers/connection.cpython-312-darwin.so
unicon/bases/routers/connection_provider.cpython-312-darwin.so
unicon/bases/routers/services.cpython-312-darwin.so
unicon/core/__init__.py
unicon/core/errors.cpython-312-darwin.so
unicon/core/manager.cpython-312-darwin.so
unicon/core/pluginmanager.cpython-312-darwin.so
unicon/database/__init__.py
unicon/database/database.cpython-312-darwin.so
unicon/eal/__init__.py
unicon/eal/bases.cpython-312-darwin.so
unicon/eal/dialog_processor.cpython-312-darwin.so
unicon/eal/dialogs.cpython-312-darwin.so
unicon/eal/expect.cpython-312-darwin.so
unicon/eal/helpers.cpython-312-darwin.so
unicon/eal/utils.cpython-312-darwin.so
unicon/eal/backend/__init__.py
unicon/eal/backend/pty_backend.cpython-312-darwin.so
unicon/eal/backend/spawn.cpython-312-darwin.so
unicon/eal/backend/telnet_backend.cpython-312-darwin.so
unicon/eal/backend/telnetlib.cpython-312-darwin.so
unicon/integration_tests/test_dialog.cpython-312-darwin.so
unicon/integration_tests/test_pyats_adapter.cpython-312-darwin.so
unicon/integration_tests/test_services.cpython-312-darwin.so
unicon/integration_tests/test_state_transitions.cpython-312-darwin.so
unicon/mock/__init__.py
unicon/mock/linenoise.cpython-312-darwin.so
unicon/mock/mock_device.cpython-312-darwin.so
unicon-25.9.dist-info/METADATA
unicon-25.9.dist-info/WHEEL
unicon-25.9.dist-info/entry_points.txt
unicon-25.9.dist-info/top_level.txt
unicon-25.9.dist-info/RECORD
