Metadata-Version: 2.1
Name: unicon
Version: 25.9
Summary: Unicon Connection Library
Home-page: https://developer.cisco.com/pyats/
Author: Cisco Systems Inc.
Author-email: pyats-support-ext@cisco.com
License: Apache 2.0
Keywords: unicon connection pyats cisco
Classifier: Development Status :: 6 - Mature
Classifier: Development Status :: 5 - Production/Stable
Classifier: Environment :: Console
Classifier: Intended Audience :: Developers
Classifier: Intended Audience :: Telecommunications Industry
Classifier: Intended Audience :: Information Technology
Classifier: Intended Audience :: System Administrators
Classifier: License :: OSI Approved :: Apache Software License
Classifier: Operating System :: MacOS
Classifier: Operating System :: POSIX :: Linux
Classifier: Programming Language :: Python :: 3.13
Classifier: Programming Language :: Python :: 3.12
Classifier: Programming Language :: Python :: 3.11
Classifier: Programming Language :: Python :: 3.10
Classifier: Programming Language :: Python :: 3.9
Classifier: Programming Language :: Python :: 3 :: Only
Classifier: Programming Language :: Python :: Implementation :: CPython
Classifier: Topic :: Software Development :: Testing
Classifier: Topic :: Software Development :: Build Tools
Classifier: Topic :: Software Development :: Libraries
Classifier: Topic :: Software Development :: Libraries :: Python Modules
Requires-Python: >=3.8
Requires-Dist: pyyaml
Requires-Dist: dill
Requires-Dist: unicon.plugins<25.10.0,>=25.9.0
Provides-Extra: dev
Requires-Dist: coverage; extra == "dev"
Requires-Dist: restview; extra == "dev"
Requires-Dist: Sphinx; extra == "dev"
Requires-Dist: sphinxcontrib-napoleon; extra == "dev"
Requires-Dist: sphinxcontrib-mockautodoc; extra == "dev"
Requires-Dist: sphinx-rtd-theme; extra == "dev"
Provides-Extra: pyats
Requires-Dist: pyats; extra == "pyats"
Provides-Extra: robot
Requires-Dist: robotframework; extra == "robot"
